abtutils/__init__.py
abtutils/dbs.py
abtutils/files.py
abtutils/times.py
abtutils-0.1.9.dist-info/licenses/LICENSE
abtutils-0.1.9.dist-info/METADATA
abtutils-0.1.9.dist-info/WHEEL
abtutils-0.1.9.dist-info/top_level.txt
abtutils-0.1.9.dist-info/RECORD
