Metadata-Version: 2.4
Name: abtutils
Version: 0.1.9
Summary: A brief description of your package
Home-page: https://github.com/AngeloBurt/abtutils
Author: AngeloBurt
Author-email: 542685010@qq.com
Classifier: Programming Language :: Python :: 3
Classifier: License :: OSI Approved :: MIT License
Classifier: Operating System :: OS Independent
Requires-Python: >=3.8
License-File: LICENSE
Provides-Extra: dev
Requires-Dist: pytest>=7.0; extra == "dev"
Requires-Dist: twine>=4.0; extra == "dev"
Dynamic: license-file
